[   
    {"label": "Atlantic \u2013 Central Mission District", "value": "AMR_CENTRAL"},
    {"label": "Atlantic \u2013 Northeast Mission District", "value": "AMR_NORTHEAST"},
    {"label": "Atlantic \u2013 Southern Mission District", "value": "AMR_SOUTHERN"},
    {"label": "Atlantic \u2013 Western Mission District", "value": "AMR_WESTERN"},
    {"label": "Canadian Mission District", "value": "CANADA"},
    {"label": "Carolinas \u2013 Catawba Valley Mission District", "value": "CMR_CATAWBA_VAL"},
    {"label": "Carolinas \u2013 Piedmont-East Mission District", "value": "CMR_PIEDMONT_E"},
    {"label": "Carolinas \u2013 South Carolina Mission District", "value": "CMR_S_CAROLINA"},
    {"label": "Carolinas \u2013 Southern Piedmont Mission District", "value": "CMR_S_PIEDMONT"},
    {"label": "Central Pacific Mission District", "value": "CENTRAL_PACIFIC"},
    {"label": "Eastern South Dakota Mission District", "value": "E_SD"},
    {"label": "Great Plains \u2013 East Mission District", "value": "GREAT_PLAINS_EAST"},
    {"label": "Great Plains \u2013 South Mission District", "value": "GREAT_PLAINS_SOUTH"},
    {"label": "Great Plains \u2013 West Mission District", "value": "GREAT_PLAINS_WEST"},
    {"label": "Great Rivers Mission District", "value": "GREAT_RIVERS"},
    {"label": "Heartland Mission District", "value": "IN_KY"},
    {"label": "Iowa Mission District", "value": "IOWA"},
    {"label": "Michigan Mission District", "value": "MI"},
    {"label": "Mid-Northeast Mission District", "value": "MID_NE"},
    {"label": "Mid-South Mission District", "value": "S_GULF_COAST"},
    {"label": "Minkota Mission District", "value": "MINKOTA"},
    {"label": "Northwest Mission District", "value": "NW"},
    {"label": "Ohio \u2013 North Central Mission District", "value": "NC_OHIO"},
    {"label": "Ohio \u2013 North Eastern Mission District", "value": "NE_OHIO"},
    {"label": "Ohio \u2013 North West Mission District", "value": "NW_OHIO"},
    {"label": "Ohio \u2013 South Eastern Mission District", "value": "SE_OHIO"},
    {"label": "Ohio \u2013 Southwest Mission District", "value": "SW_OHIO"},
    {"label": "Rocky Mountain Mission District", "value": "ROCKY_MTN"},
    {"label": "Sonshine Mission District", "value": "FLORIDA"},
    {"label": "South West Pacific Mission District", "value": "S_CAL_S_NV_AZ"},
    {"label": "Texas \u2013 North Texas Mission District", "value": "N_TX"},
    {"label": "Texas \u2013 Southeast Texas Mission District", "value": "SOUTHEAST_TEXAS"},
    {"label": "Texas \u2013 Southwest Texas Mission District", "value": "SOUTHWEST_TEXAS"},
    {"label": "Western Dakotas/Montana/Wyoming Mission District", "value": "W_DAK_MT_WY"},
    {"label": "Wisconsin/Upper Michigan Mission District", "value": "WI_UPPER_MI"}
]
